convnext_unet/__init__.py
convnext_unet/decoder.py
convnext_unet/encoder.py
convnext_unet-0.0.5.dist-info/LICENSE
convnext_unet-0.0.5.dist-info/METADATA
convnext_unet-0.0.5.dist-info/WHEEL
convnext_unet-0.0.5.dist-info/top_level.txt
convnext_unet-0.0.5.dist-info/RECORD
