Metadata-Version: 2.1
Name: convnext-unet
Version: 0.0.5
Summary: Unet model with ConvNext as its encoder.
Author-email: Tianyi Wang <2019302443@mail.nwpu.edu.cn>
License: GNU GENERAL PUBLIC LICENSE
Project-URL: Homepage, https://github.com/NPU-Franklin/ConvNeXt-Unet
Project-URL: Bug Tracker, https://github.com/NPU-Franklin/ConvNeXt-Unet/issues
Classifier: Development Status :: 3 - Alpha
Classifier: Programming Language :: Python :: 3
Classifier: License :: OSI Approved :: GNU General Public License v3 (GPLv3)
Classifier: Operating System :: OS Independent
Requires-Python: >=3.7
License-File: LICENSE
Requires-Dist: torch
Requires-Dist: timm
Requires-Dist: segmentation-models-pytorch
